frisk_sdk/.gitignore
frisk_sdk/__init__.py
frisk_sdk/_core.abi3.so
frisk_sdk/_experimental/__init__.py
frisk_sdk/_experimental/agent_stream_rewriter.py
frisk_sdk/_experimental/content_block_utils.py
frisk_sdk/_experimental/drop_token_events_callback_handler.py
frisk_sdk/_experimental/frisk_llm_output_middleware.py
frisk_sdk/_experimental/message_chunk_transformer.py
frisk_sdk/_experimental/message_transformer.py
frisk_sdk/_experimental/rewriting_chat_model.py
frisk_sdk/_experimental/stream_transformer.py
frisk_sdk/adapters/__init__.py
frisk_sdk/adapters/langchain/__init__.py
frisk_sdk/adapters/langchain/frisk_callback_handler.py
frisk_sdk/adapters/langchain/frisk_langchain.py
frisk_sdk/adapters/langchain/frisk_tool_middleware.py
frisk_sdk/core/__init__.py
frisk_sdk/core/frisk.py
frisk_sdk/core/frisk_session.py
frisk_sdk/core/token_manager.py
frisk_sdk/core/tool_call_span.py
frisk_sdk/errors/__init__.py
frisk_sdk/errors/api_response_errors/__init__.py
frisk_sdk/errors/api_response_errors/raise_frisk_api_error.py
frisk_sdk/errors/configuration_errors/__init__.py
frisk_sdk/errors/frisk_error.py
frisk_sdk/errors/invocation_errors/__init__.py
frisk_sdk/framework_adapter/__init__.py
frisk_sdk/framework_adapter/base_framework_adapter.py
frisk_sdk/framework_adapter/framework_adapter.py
frisk_sdk/telemetry/__init__.py
frisk_sdk/telemetry/get_tracer.py
frisk_sdk/telemetry/init_tracing.py
frisk_sdk-0.1.3.dist-info/METADATA
frisk_sdk-0.1.3.dist-info/WHEEL
frisk_sdk-0.1.3.dist-info/RECORD
