Metadata-Version: 2.4
Name: frisk-sdk
Version: 0.1.3
Requires-Dist: langchain>=1.0.2
Requires-Dist: langchain-core>=1.2.0
Requires-Dist: langchain-openai>=1.0.1
Requires-Dist: langgraph>=1.0.1
Requires-Dist: pydantic>=2.12.3
Requires-Dist: langchain-experimental>=0.0.42
Requires-Dist: langchain-mcp-adapters>=0.1.12
Requires-Dist: pydash>=8.0.5
Requires-Dist: opentelemetry-sdk>=1.38.0
Requires-Dist: opentelemetry-exporter-otlp-proto-grpc>=1.38.0
Requires-Dist: requests>=2.31.0
Requires-Dist: asyncio>=4.0.0
Requires-Dist: cuid2>=2.0.1
Requires-Dist: pyright>=1.1.407 ; extra == 'dev'
Requires-Dist: ruff>=0.14.2 ; extra == 'dev'
Requires-Dist: pytest>=8.0.0 ; extra == 'dev'
Requires-Dist: pytest-cov>=5 ; extra == 'dev'
Provides-Extra: dev
Summary: Frisk AI Python SDK
Author: FriskAI
Requires-Python: >=3.12
Project-URL: Homepage, https://friskai.com
